LICENSE.txt
MANIFEST.in
README.rst
__init__.py
requirements.txt
setup.cfg
setup.py
util.py
vaderSentiment_fr/__init__.py
vaderSentiment_fr/emoji_utf8_lexicon.txt
vaderSentiment_fr/emojis_fr.txt
vaderSentiment_fr/fr_lexicon.txt
vaderSentiment_fr/no_negate.txt
vaderSentiment_fr/tree.py
vaderSentiment_fr/vaderSentiment.py
vaderSentiment_fr/vader_lexicon.txt
vaderSentiment_fr.egg-info/PKG-INFO
vaderSentiment_fr.egg-info/SOURCES.txt
vaderSentiment_fr.egg-info/dependency_links.txt
vaderSentiment_fr.egg-info/requires.txt
vaderSentiment_fr.egg-info/top_level.txt