Metadata-Version: 2.1
Name: vaderSentiment-fr
Version: 1.3
Summary: UNKNOWN
Home-page: https://github.com/thomas7lieues/vader_FR
Author: DEPREZ Olivier, EK Thomas
Author-email: olivier@7lieues.io, thomas@7lieues.io
License: MIT
Download-URL: https://github.com/thomas7lieues/vader_FR/archive/v_0.1.tar.gz
Keywords: Vader_FR,vaderSentiment,Vader,Sentiment,French,Analysis
Platform: UNKNOWN
Classifier: Development Status :: 3 - Alpha
Classifier: Intended Audience :: Developers
Classifier: Topic :: Software Development :: Build Tools
Classifier: License :: OSI Approved :: MIT License
Classifier: Programming Language :: Python :: 3
Classifier: Programming Language :: Python :: 3.4
Classifier: Programming Language :: Python :: 3.5
Classifier: Programming Language :: Python :: 3.6
